pkonfig/__init__.py
pkonfig/base_config.py
pkonfig/config.py
pkonfig/descriptor_helper.py
pkonfig/errors.py
pkonfig/fields.py
pkonfig/storage/__init__.py
pkonfig/storage/base.py
pkonfig/storage/dot_env.py
pkonfig/storage/env.py
pkonfig/storage/ini.py
pkonfig/storage/json.py
pkonfig/storage/toml.py
pkonfig/storage/yaml_.py
pkonfig-2.1.1.dist-info/METADATA
pkonfig-2.1.1.dist-info/WHEEL
pkonfig-2.1.1.dist-info/licenses/LICENSE
pkonfig-2.1.1.dist-info/RECORD
