Metadata-Version: 2.4
Name: pkonfig
Version: 2.1.1
Summary: Pythonic agile application configuration helpers
License: MIT
License-File: LICENSE
Keywords: config,configuration,configurations,settings,env,environment,environments,dotenv,application,python-config,yaml,toml,ini
Author: Nikita Gladkikh
Author-email: gladkikh.nikita@gmail.com
Requires-Python: >=3.9,<4.0
Classifier: Development Status :: 5 - Production/Stable
Classifier: Intended Audience :: Developers
Classifier: Intended Audience :: System Administrators
Classifier: License :: OSI Approved :: MIT License
Classifier: Operating System :: OS Independent
Classifier: Programming Language :: Python
Classifier: Programming Language :: Python :: 3
Classifier: Programming Language :: Python :: 3.9
Classifier: Programming Language :: Python :: 3.10
Classifier: Programming Language :: Python :: 3.11
Classifier: Programming Language :: Python :: 3.12
Classifier: Programming Language :: Python :: 3.13
Classifier: Programming Language :: Python :: 3.14
Classifier: Programming Language :: Python :: 3 :: Only
Classifier: Topic :: Software Development :: Libraries :: Python Modules
Classifier: Typing :: Typed
Provides-Extra: toml
Provides-Extra: yaml
Requires-Dist: pyyaml ; extra == "yaml"
Requires-Dist: tomli ; extra == "toml"
Requires-Dist: typing_extensions (>=4.12.0) ; python_version < "3.13"
Project-URL: documentation, https://ngladkikh.github.io/pkonfig/
Project-URL: homepage, https://github.com/ngladkikh/pkonfig
Project-URL: repository, https://github.com/ngladkikh/pkonfig
